aw_export_timewarrior/__init__.py
aw_export_timewarrior/aw_client.py
aw_export_timewarrior/cli.py
aw_export_timewarrior/compare.py
aw_export_timewarrior/config.py
aw_export_timewarrior/config_validation.py
aw_export_timewarrior/export.py
aw_export_timewarrior/main.py
aw_export_timewarrior/output.py
aw_export_timewarrior/report.py
aw_export_timewarrior/retag.py
aw_export_timewarrior/state.py
aw_export_timewarrior/tag_extractor.py
aw_export_timewarrior/time_tracker.py
aw_export_timewarrior/timew_tracker.py
aw_export_timewarrior/utils.py
aw_export_timewarrior-0.0.0.dist-info/METADATA
aw_export_timewarrior-0.0.0.dist-info/WHEEL
aw_export_timewarrior-0.0.0.dist-info/entry_points.txt
aw_export_timewarrior-0.0.0.dist-info/licenses/LICENSE.TXT
aw_export_timewarrior-0.0.0.dist-info/RECORD
