Metadata-Version: 2.4
Name: aw-export-timewarrior
Version: 0.0.0
Summary: Export ActivityWatch data to TimeWarrior with rule-based tag categorization
License: MIT
License-File: LICENSE.TXT
Keywords: activitywatch,timewarrior,time-tracking,productivity
Author: Tobias Brox
Author-email: tobias@redpill-linpro.com
Requires-Python: >=3.13
Classifier: Development Status :: 4 - Beta
Classifier: Environment :: Console
Classifier: Intended Audience :: End Users/Desktop
Classifier: License :: OSI Approved :: MIT License
Classifier: Operating System :: POSIX :: Linux
Classifier: Programming Language :: Python :: 3
Classifier: Programming Language :: Python :: 3.13
Classifier: Topic :: Utilities
Provides-Extra: dev
Requires-Dist: aw-client
Requires-Dist: dateparser (>=1.0.0)
Requires-Dist: pre-commit (>=3.0.0) ; extra == "dev"
Requires-Dist: pytest (>=8.0.0) ; extra == "dev"
Requires-Dist: pytest-cov (>=4.0.0) ; extra == "dev"
Requires-Dist: ruff (>=0.8.0) ; extra == "dev"
Requires-Dist: termcolor (>=3.1.0,<4.0.0)
Project-URL: Changelog, https://github.com/tobixen/aw-export-timewarrior/blob/main/CHANGELOG.md
Project-URL: Documentation, https://github.com/tobixen/aw-export-timewarrior#readme
Project-URL: Homepage, https://github.com/tobixen/aw-export-timewarrior
Project-URL: Issues, https://github.com/tobixen/aw-export-timewarrior/issues
Project-URL: Repository, https://github.com/tobixen/aw-export-timewarrior
